odoo/addons/fleet_vehicle_configuration/README.rst
odoo/addons/fleet_vehicle_configuration/__init__.py
odoo/addons/fleet_vehicle_configuration/__manifest__.py
odoo/addons/fleet_vehicle_configuration/i18n/es.po
odoo/addons/fleet_vehicle_configuration/i18n/fleet_vehicle_configuration.pot
odoo/addons/fleet_vehicle_configuration/i18n/it.po
odoo/addons/fleet_vehicle_configuration/i18n/pt_BR.po
odoo/addons/fleet_vehicle_configuration/i18n/sv.po
odoo/addons/fleet_vehicle_configuration/models/__init__.py
odoo/addons/fleet_vehicle_configuration/models/fleet_configuration.py
odoo/addons/fleet_vehicle_configuration/models/fleet_vehicle.py
odoo/addons/fleet_vehicle_configuration/readme/CONTRIBUTORS.md
odoo/addons/fleet_vehicle_configuration/readme/DESCRIPTION.md
odoo/addons/fleet_vehicle_configuration/security/ir.model.access.csv
odoo/addons/fleet_vehicle_configuration/static/description/icon.png
odoo/addons/fleet_vehicle_configuration/static/description/index.html
odoo/addons/fleet_vehicle_configuration/views/fleet_vehicle.xml
odoo/addons/fleet_vehicle_configuration/views/fleet_vehicle_configuration.xml
odoo_addon_fleet_vehicle_configuration-18.0.1.0.0.3.dist-info/METADATA
odoo_addon_fleet_vehicle_configuration-18.0.1.0.0.3.dist-info/WHEEL
odoo_addon_fleet_vehicle_configuration-18.0.1.0.0.3.dist-info/top_level.txt
odoo_addon_fleet_vehicle_configuration-18.0.1.0.0.3.dist-info/RECORD
